{
    "index": "046",
    "verse": {
        "verse_0": {
            "file": "000.mp3",
            "size": 26642,
            "unit": "26,02 KB"
        },
        "verse_1": {
            "file": "001.mp3",
            "size": 21287,
            "unit": "20,79 KB"
        },
        "verse_2": {
            "file": "002.mp3",
            "size": 32128,
            "unit": "31,38 KB"
        },
        "verse_3": {
            "file": "003.mp3",
            "size": 92732,
            "unit": "90,56 KB"
        },
        "verse_4": {
            "file": "004.mp3",
            "size": 158430,
            "unit": "154,72 KB"
        },
        "verse_5": {
            "file": "005.mp3",
            "size": 83067,
            "unit": "81,12 KB"
        },
        "verse_6": {
            "file": "006.mp3",
            "size": 56292,
            "unit": "54,97 KB"
        },
        "verse_7": {
            "file": "007.mp3",
            "size": 76666,
            "unit": "74,87 KB"
        },
        "verse_8": {
            "file": "008.mp3",
            "size": 106838,
            "unit": "104,33 KB"
        },
        "verse_9": {
            "file": "009.mp3",
            "size": 94300,
            "unit": "92,09 KB"
        },
        "verse_10": {
            "file": "010.mp3",
            "size": 114805,
            "unit": "112,11 KB"
        },
        "verse_11": {
            "file": "011.mp3",
            "size": 91949,
            "unit": "89,79 KB"
        },
        "verse_12": {
            "file": "012.mp3",
            "size": 91295,
            "unit": "89,16 KB"
        },
        "verse_13": {
            "file": "013.mp3",
            "size": 60863,
            "unit": "59,44 KB"
        },
        "verse_14": {
            "file": "014.mp3",
            "size": 78103,
            "unit": "76,27 KB"
        },
        "verse_15": {
            "file": "015.mp3",
            "size": 263312,
            "unit": "257,14 KB"
        },
        "verse_16": {
            "file": "016.mp3",
            "size": 102528,
            "unit": "100,13 KB"
        },
        "verse_17": {
            "file": "017.mp3",
            "size": 176063,
            "unit": "171,94 KB"
        },
        "verse_18": {
            "file": "018.mp3",
            "size": 128781,
            "unit": "125,76 KB"
        },
        "verse_19": {
            "file": "019.mp3",
            "size": 57989,
            "unit": "56,63 KB"
        },
        "verse_20": {
            "file": "020.mp3",
            "size": 140275,
            "unit": "136,99 KB"
        },
        "verse_21": {
            "file": "021.mp3",
            "size": 143541,
            "unit": "140,18 KB"
        },
        "verse_22": {
            "file": "022.mp3",
            "size": 67132,
            "unit": "65,56 KB"
        },
        "verse_23": {
            "file": "023.mp3",
            "size": 77320,
            "unit": "75,51 KB"
        },
        "verse_24": {
            "file": "024.mp3",
            "size": 96389,
            "unit": "94,13 KB"
        },
        "verse_25": {
            "file": "025.mp3",
            "size": 76275,
            "unit": "74,49 KB"
        },
        "verse_26": {
            "file": "026.mp3",
            "size": 190560,
            "unit": "186,09 KB"
        },
        "verse_27": {
            "file": "027.mp3",
            "size": 56553,
            "unit": "55,23 KB"
        },
        "verse_28": {
            "file": "028.mp3",
            "size": 86724,
            "unit": "84,69 KB"
        },
        "verse_29": {
            "file": "029.mp3",
            "size": 109711,
            "unit": "107,14 KB"
        },
        "verse_30": {
            "file": "030.mp3",
            "size": 123949,
            "unit": "121,04 KB"
        },
        "verse_31": {
            "file": "031.mp3",
            "size": 74446,
            "unit": "72,7 KB"
        },
        "verse_32": {
            "file": "032.mp3",
            "size": 86071,
            "unit": "84,05 KB"
        },
        "verse_33": {
            "file": "033.mp3",
            "size": 112977,
            "unit": "110,33 KB"
        },
        "verse_34": {
            "file": "034.mp3",
            "size": 90642,
            "unit": "88,52 KB"
        },
        "verse_35": {
            "file": "035.mp3",
            "size": 136749,
            "unit": "133,54 KB"
        }
    },
    "count": 35
}
